prof/__init__.py
prof/main.py
prof_qx-0.0.5.dist-info/METADATA
prof_qx-0.0.5.dist-info/WHEEL
prof_qx-0.0.5.dist-info/entry_points.txt
prof_qx-0.0.5.dist-info/top_level.txt
prof_qx-0.0.5.dist-info/RECORD
