Metadata-Version: 2.4
Name: prof-qx
Version: 0.0.5
Summary: An intelligent automated trading bot for Quotex, featuring real-time trading, Telegram signal integration, and Martingale strategy
Author-email: Professor1Trader <professor1trader@example.com>
Classifier: Programming Language :: Python :: 3
Classifier: License :: OSI Approved :: MIT License
Classifier: Operating System :: OS Independent
Requires-Python: >=3.7
Requires-Dist: rich
Requires-Dist: telethon
Requires-Dist: pyfiglet
Requires-Dist: httpx
Requires-Dist: websocket-client
Requires-Dist: beautifulsoup4
Requires-Dist: certifi
Requires-Dist: pysocks
